<?xml version="1.0" encoding="utf-8"?>
<Match No="9" Version="134">
  <Status>2</Status>
  <Length Set1="23" Set2="17" Set3="21" />
  <TeamA Code="TPE">
    <Captain>7</Captain>
    <Score>0</Score>
    <Set No="1">
      <Score>19</Score>
      <Roster p3="2" p1="3" p4="7" p6="8" p5="11" p2="18" r11="13" r8="12" r7="16" l1="10" />
      <Statistics>
        <Team OppError="7" />
        <Player NoShirt="2" AtkPoint="2" BlkPoint="0" SrvPoint="0" />
        <Player NoShirt="3" AtkPoint="0" BlkPoint="0" SrvPoint="0" />
        <Player NoShirt="4" AtkPoint="0" BlkPoint="0" SrvPoint="0" />
        <Player NoShirt="5" AtkPoint="0" BlkPoint="0" SrvPoint="0" />
        <Player NoShirt="7" AtkPoint="2" BlkPoint="1" SrvPoint="0" />
        <Player NoShirt="8" AtkPoint="0" BlkPoint="0" SrvPoint="0" />
        <Player NoShirt="10" AtkPoint="0" BlkPoint="0" SrvPoint="0" />
        <Player NoShirt="11" AtkPoint="3" BlkPoint="0" SrvPoint="0" />
        <Player NoShirt="12" AtkPoint="0" BlkPoint="0" SrvPoint="0" />
        <Player NoShirt="13" AtkPoint="2" BlkPoint="0" SrvPoint="0" />
        <Player NoShirt="16" AtkPoint="0" BlkPoint="0" SrvPoint="0" />
        <Player NoShirt="18" AtkPoint="2" BlkPoint="0" SrvPoint="0" />
      </Statistics>
    </Set>
    <Set No="2">
      <Score>9</Score>
      <Roster p3="2" p1="3" p4="7" p6="12" p5="13" p2="18" r13="11" r7="16" l1="10" />
      <Statistics>
        <Team OppError="3" />
        <Player NoShirt="2" AtkPoint="0" BlkPoint="0" SrvPoint="0" />
        <Player NoShirt="3" AtkPoint="0" BlkPoint="0" SrvPoint="0" />
        <Player NoShirt="4" AtkPoint="0" BlkPoint="0" SrvPoint="0" />
        <Player NoShirt="5" AtkPoint="0" BlkPoint="0" SrvPoint="0" />
        <Player NoShirt="7" AtkPoint="0" BlkPoint="0" SrvPoint="0" />
        <Player NoShirt="8" AtkPoint="0" BlkPoint="0" SrvPoint="0" />
        <Player NoShirt="10" AtkPoint="0" BlkPoint="0" SrvPoint="0" />
        <Player NoShirt="11" AtkPoint="0" BlkPoint="0" SrvPoint="0" />
        <Player NoShirt="12" AtkPoint="2" BlkPoint="0" SrvPoint="0" />
        <Player NoShirt="13" AtkPoint="2" BlkPoint="0" SrvPoint="0" />
        <Player NoShirt="16" AtkPoint="0" BlkPoint="0" SrvPoint="0" />
        <Player NoShirt="18" AtkPoint="1" BlkPoint="1" SrvPoint="0" />
      </Statistics>
    </Set>
    <Set No="3">
      <Score>13</Score>
      <Roster p3="2" p1="3" p4="7" p6="12" p5="13" p2="18" r18="5" r2="8" l1="10" />
      <Statistics>
        <Team OppError="4" />
        <Player NoShirt="2" AtkPoint="1" BlkPoint="0" SrvPoint="0" />
        <Player NoShirt="3" AtkPoint="0" BlkPoint="0" SrvPoint="0" />
        <Player NoShirt="4" AtkPoint="0" BlkPoint="0" SrvPoint="0" />
        <Player NoShirt="5" AtkPoint="0" BlkPoint="0" SrvPoint="0" />
        <Player NoShirt="7" AtkPoint="2" BlkPoint="0" SrvPoint="0" />
        <Player NoShirt="8" AtkPoint="0" BlkPoint="0" SrvPoint="0" />
        <Player NoShirt="10" AtkPoint="0" BlkPoint="0" SrvPoint="0" />
        <Player NoShirt="11" AtkPoint="0" BlkPoint="0" SrvPoint="0" />
        <Player NoShirt="12" AtkPoint="1" BlkPoint="0" SrvPoint="0" />
        <Player NoShirt="13" AtkPoint="3" BlkPoint="0" SrvPoint="0" />
        <Player NoShirt="16" AtkPoint="0" BlkPoint="0" SrvPoint="0" />
        <Player NoShirt="18" AtkPoint="2" BlkPoint="0" SrvPoint="0" />
      </Statistics>
    </Set>
  </TeamA>
  <TeamB Code="BRA">
    <Captain>2</Captain>
    <Score>3</Score>
    <Set No="1">
      <Score>25</Score>
      <Roster p2="2" p6="4" p1="5" p4="9" p3="11" p5="13" r2="18" r13="8" l1="14" />
      <Statistics>
        <Team OppError="6" />
        <Player NoShirt="2" AtkPoint="1" BlkPoint="0" SrvPoint="0" />
        <Player NoShirt="4" AtkPoint="4" BlkPoint="0" SrvPoint="0" />
        <Player NoShirt="5" AtkPoint="2" BlkPoint="0" SrvPoint="0" />
        <Player NoShirt="6" AtkPoint="0" BlkPoint="0" SrvPoint="0" />
        <Player NoShirt="8" AtkPoint="0" BlkPoint="0" SrvPoint="0" />
        <Player NoShirt="9" AtkPoint="3" BlkPoint="1" SrvPoint="0" />
        <Player NoShirt="10" AtkPoint="0" BlkPoint="0" SrvPoint="0" />
        <Player NoShirt="11" AtkPoint="1" BlkPoint="1" SrvPoint="0" />
        <Player NoShirt="13" AtkPoint="1" BlkPoint="2" SrvPoint="1" />
        <Player NoShirt="14" AtkPoint="0" BlkPoint="0" SrvPoint="0" />
        <Player NoShirt="17" AtkPoint="0" BlkPoint="0" SrvPoint="0" />
        <Player NoShirt="18" AtkPoint="1" BlkPoint="0" SrvPoint="1" />
      </Statistics>
    </Set>
    <Set No="2">
      <Score>25</Score>
      <Roster p1="2" p5="4" p6="5" p3="9" p2="11" p4="13" l1="14" />
      <Statistics>
        <Team OppError="6" />
        <Player NoShirt="2" AtkPoint="0" BlkPoint="0" SrvPoint="2" />
        <Player NoShirt="4" AtkPoint="4" BlkPoint="1" SrvPoint="0" />
        <Player NoShirt="5" AtkPoint="0" BlkPoint="1" SrvPoint="1" />
        <Player NoShirt="6" AtkPoint="0" BlkPoint="0" SrvPoint="0" />
        <Player NoShirt="8" AtkPoint="0" BlkPoint="0" SrvPoint="0" />
        <Player NoShirt="9" AtkPoint="3" BlkPoint="0" SrvPoint="1" />
        <Player NoShirt="10" AtkPoint="0" BlkPoint="0" SrvPoint="0" />
        <Player NoShirt="11" AtkPoint="2" BlkPoint="0" SrvPoint="0" />
        <Player NoShirt="13" AtkPoint="3" BlkPoint="1" SrvPoint="0" />
        <Player NoShirt="14" AtkPoint="0" BlkPoint="0" SrvPoint="0" />
        <Player NoShirt="17" AtkPoint="0" BlkPoint="0" SrvPoint="0" />
        <Player NoShirt="18" AtkPoint="0" BlkPoint="0" SrvPoint="0" />
      </Statistics>
    </Set>
    <Set No="3">
      <Score>25</Score>
      <Roster p2="2" p6="4" p1="5" p4="9" p3="10" p5="13" r4="18" r2="17" r13="8" l1="14" />
      <Statistics>
        <Team OppError="5" />
        <Player NoShirt="2" AtkPoint="0" BlkPoint="0" SrvPoint="0" />
        <Player NoShirt="4" AtkPoint="2" BlkPoint="0" SrvPoint="0" />
        <Player NoShirt="5" AtkPoint="2" BlkPoint="0" SrvPoint="0" />
        <Player NoShirt="6" AtkPoint="0" BlkPoint="0" SrvPoint="0" />
        <Player NoShirt="8" AtkPoint="0" BlkPoint="0" SrvPoint="0" />
        <Player NoShirt="9" AtkPoint="2" BlkPoint="2" SrvPoint="0" />
        <Player NoShirt="10" AtkPoint="2" BlkPoint="0" SrvPoint="0" />
        <Player NoShirt="11" AtkPoint="0" BlkPoint="0" SrvPoint="0" />
        <Player NoShirt="13" AtkPoint="5" BlkPoint="2" SrvPoint="0" />
        <Player NoShirt="14" AtkPoint="0" BlkPoint="0" SrvPoint="0" />
        <Player NoShirt="17" AtkPoint="2" BlkPoint="0" SrvPoint="0" />
        <Player NoShirt="18" AtkPoint="1" BlkPoint="0" SrvPoint="0" />
      </Statistics>
    </Set>
  </TeamB>
</Match>