<?xml version="1.0" encoding="utf-8"?>
<Match No="60" Version="241">
  <Status>2</Status>
  <TeamA Code="FIN">
    <Score>3</Score>
    <Set No="1">
      <Score>25</Score>
    </Set>
    <Set No="2">
      <Score>25</Score>
    </Set>
    <Set No="3">
      <Score>26</Score>
    </Set>
    <Set No="5" />
  </TeamA>
  <TeamB Code="CAN">
    <Set No="1">
      <Score>19</Score>
    </Set>
    <Set No="2">
      <Score>22</Score>
    </Set>
    <Set No="3">
      <Score>24</Score>
    </Set>
    <Set No="5" />
  </TeamB>
  <Length Set1="28" Set2="33" Set3="32" />
</Match>